{
  "builtInLibrariesFolders": "C:\\KidCode\\arduino\\libraries",
  "customBuildProperties": "build.warn_data_percentage=75,runtime.tools.xtensa-esp-elf-gdb.path=C:\\Users\\HOXUANPHU\\AppData\\Local\\Arduino15\\packages\\esp32\\tools\\xtensa-esp-elf-gdb\\11.2_20220823,runtime.tools.esptool_py.path=C:\\Users\\HOXUANPHU\\AppData\\Local\\Arduino15\\packages\\esp32\\tools\\esptool_py\\4.5.1,runtime.tools.riscv32-esp-elf-gcc.path=C:\\Users\\HOXUANPHU\\AppData\\Local\\Arduino15\\packages\\esp32\\tools\\riscv32-esp-elf-gcc\\esp-2021r2-patch5-8.4.0,runtime.tools.xtensa-esp32-elf-gcc.path=C:\\Users\\HOXUANPHU\\AppData\\Local\\Arduino15\\packages\\esp32\\tools\\xtensa-esp32-elf-gcc\\esp-2021r2-patch5-8.4.0,runtime.tools.xtensa-esp32s3-elf-gcc.path=C:\\Users\\HOXUANPHU\\AppData\\Local\\Arduino15\\packages\\esp32\\tools\\xtensa-esp32s3-elf-gcc\\esp-2021r2-patch5-8.4.0,runtime.tools.riscv32-esp-elf-gdb.path=C:\\Users\\HOXUANPHU\\AppData\\Local\\Arduino15\\packages\\esp32\\tools\\riscv32-esp-elf-gdb\\11.2_20220823,runtime.tools.openocd-esp32.path=C:\\Users\\HOXUANPHU\\AppData\\Local\\Arduino15\\packages\\esp32\\tools\\openocd-esp32\\v0.11.0-esp32-20221026,runtime.tools.xtensa-esp32s2-elf-gcc.path=C:\\Users\\HOXUANPHU\\AppData\\Local\\Arduino15\\packages\\esp32\\tools\\xtensa-esp32s2-elf-gcc\\esp-2021r2-patch5-8.4.0,runtime.tools.dfu-util.path=C:\\Users\\HOXUANPHU\\AppData\\Local\\Arduino15\\packages\\arduino\\tools\\dfu-util\\0.11.0-arduino5,runtime.tools.mkspiffs.path=C:\\Users\\HOXUANPHU\\AppData\\Local\\Arduino15\\packages\\esp32\\tools\\mkspiffs\\0.2.3,runtime.tools.mklittlefs.path=C:\\Users\\HOXUANPHU\\AppData\\Local\\Arduino15\\packages\\esp32\\tools\\mklittlefs\\3.0.0-gnu12-dc7f933",
  "fqbn": "esp32:esp32:esp32doit-devkit-v1",
  "hardwareFolders": "C:\\KidCode\\arduino\\hardware,C:\\Users\\HOXUANPHU\\AppData\\Local\\Arduino15\\packages",
  "otherLibrariesFolders": "C:\\Users\\HOXUANPHU\\OneDrive\\Documents\\Arduino\\libraries",
  "runtime.ide.version": "10801",
  "sketchLocation": "C:\\Kidscode_test\\KidsCode\\KidscodeSketch\\KidscodeSketch.ino",
  "toolsFolders": "C:\\KidCode\\arduino\\tools-builder,C:\\KidCode\\arduino\\hardware\\tools\\avr,C:\\Users\\HOXUANPHU\\AppData\\Local\\Arduino15\\packages"
}